dfstats/__init__.py
dfstats/dfstats.py
dfstats/utils.py
dfstats-0.0.1.dist-info/METADATA
dfstats-0.0.1.dist-info/WHEEL
dfstats-0.0.1.dist-info/licenses/LICENSE
dfstats-0.0.1.dist-info/RECORD
